{
  "project_info": {
    "project_id": "barrons-1100-for-gre",
    "project_number": "460876026961",
    "name": "Barron\u0027s 1100 for GRE"
  },
  "client": [
    {
      "client_info": {
        "mobilesdk_app_id": "1:460876026961:android:7938ae5f46e2839f",
        "client_id": "android:fightingpit.barrons1100",
        "client_type": 1,
        "android_client_info": {
          "package_name": "fightingpit.barrons1100"
        }
      },
      "oauth_client": [],
      "api_key": [],
      "services": {
        "analytics_service": {
          "status": 2,
          "analytics_property": {
            "tracking_id": "UA-70784730-2"
          }
        },
        "cloud_messaging_service": {
          "status": 1,
          "apns_config": []
        },
        "appinvite_service": {
          "status": 1,
          "other_platform_oauth_client": []
        },
        "google_signin_service": {
          "status": 1
        },
        "ads_service": {
          "status": 1
        }
      }
    }
  ],
  "client_info": [],
  "ARTIFACT_VERSION": "1"
}